Metadata-Version: 2.1
Name: anitub-lib
Version: 0.1.1
Summary: Library that parses data from the site anitube.in.ua
Home-page: https://github.com/Lorg0n/anitube-ua-lib
Author: Lorg0n
